LICENSE
README.md
setup.cfg
setup.py
pyodbc_extras/__init__.py
pyodbc_extras.egg-info/PKG-INFO
pyodbc_extras.egg-info/SOURCES.txt
pyodbc_extras.egg-info/dependency_links.txt
pyodbc_extras.egg-info/top_level.txt