Metadata-Version: 2.4
Name: pyodbc-extras
Version: 0.0.0
Summary: Extra Methods for Working with ODBC Connections in Python
Home-page: https://github.com/DanielJDufour/pyodbc-extras
Download-URL: https://github.com/DanielJDufour/pyodbc-extras/tarball/download
Author: Daniel J. Dufour
Author-email: daniel.j.dufour@gmail.com
Keywords: data,odbc,python,sql
Classifier: Development Status :: 4 - Beta
Classifier: Programming Language :: Python :: 3
Classifier: License :: CC0 1.0 Universal (CC0 1.0) Public Domain Dedication
Classifier: Operating System :: OS Independent
License-File: LICENSE
Dynamic: author
Dynamic: author-email
Dynamic: classifier
Dynamic: description
Dynamic: description-content-type
Dynamic: download-url
Dynamic: home-page
Dynamic: keywords
Dynamic: license-file
Dynamic: summary
